[{"id":28962548,"path":"/график работы","description":"Ведет в родительский стейт, наполняется без деталей","enabled":true,"shared":false,"phrases":[{"text":"где в анкете указать потенциальный график работы"},{"text":"как обозначить предпочитаемое время работы  "},{"text":"нужно ли указывать часы работы в резюме  "},{"text":"где прописать желаемый график  "},{"text":"как отметить доступность в определенные часы  "},{"text":"где в заявке указать рабочие часы  "},{"text":"как указать гибкий график  "},{"text":"где отметить возможность сменного графика  "},{"text":"как отразить в резюме часы занятости  "},{"text":"где в профиле указать время работы  "},{"text":"как зафиксировать предпочитаемый график  "},{"text":"где писать о готовности к ночным сменам "},{"text":"где в форме указать часы доступности  "},{"text":"как отметить частичную занятость в анкете  "},{"text":"где в документе прописать рабочие часы  "},{"text":"как указать возможность работы по выходным  "},{"text":"где в заявлении отметить график  "},{"text":"как отразить в анкете гибкое время  "},{"text":"где в резюме указать часы работы  "},{"text":"как обозначить ограничения по времени  "},{"text":"нужно ли указывать предпочитаемые часы в резюме  "},{"text":"где в профиле отметить график  "},{"text":"как прописать возможность работы вечером  "},{"text":"где в форме указать сменный график  "},{"text":"как отметить в резюме часы доступности"}],"classificationRules":{"refs":[]},"patterns":[],"priority":0},{"id":28962549,"path":"/частичная занятость","description":"Ведет в родительский стейт, наполняется без деталей","enabled":true,"shared":false,"phrases":[{"text":"ищу возможность дополнительного заработка  "},{"text":"требуется работа на неполный день  "},{"text":"рассматриваю варианты с гибким графиком  "},{"text":"хочу совмещать с основным занятием  "},{"text":"требуется подработка на выходные  "},{"text":"ищу работу с частичной занятостью  "},{"text":"нужен дополнительный доход по вечерам  "},{"text":"ищу подработку без привязки к графику  "},{"text":"требуется временная занятость на месяц  "},{"text":"рассматриваю неполную занятость в будни  "},{"text":"готова к подработке в выходные дни  "},{"text":"ищу варианты с почасовой оплатой  "},{"text":"требуется подработка для студентов  "},{"text":"нужен свободный график с частичной нагрузкой  "},{"text":"ищу подработку с ежедневной оплатой  "},{"text":"требуется занятость на несколько часов в день  "},{"text":"нужна работа без долгосрочных обязательств  "},{"text":"рассматриваю подработку в сфере услуг  "},{"text":"готов к труду по вечерам"},{"text":"хотел бы взять проект в качестве занятости"}],"classificationRules":{"refs":[]},"patterns":[],"priority":0},{"id":28962550,"path":"/не получается оплатить","description":"","enabled":true,"shared":false,"phrases":[{"text":"не получается оплатить"},{"text":"ошибка оплаты"},{"text":"не могу оплатить"},{"text":"не выходит провести оплату"},{"text":"платеж не проходит"},{"text":"оплата не возможна"},{"text":"не удается произвести оплату"},{"text":"проблемы с оплатой"},{"text":"не могу провести оплату"},{"text":"оплата не проходит"},{"text":"ошибка при оплате"},{"text":"не получается произвести оплату"},{"text":"платеж не удается"},{"text":"оплата не доступна"},{"text":"не могу оплатить сейчас"},{"text":"проблемы с платежом"},{"text":"не выходит оплатить"},{"text":"оплата не проходит успешно"},{"text":"не удается оплатить"},{"text":"платеж не возможен"},{"text":"ошибка в процессе оплаты"},{"text":"не могу произвести оплату"},{"text":"оплата не проходит нормально"},{"text":"проблемы с оплатой заказа"},{"text":"не получается провести оплату"},{"text":"оплата не доступна сейчас"},{"text":"не могу оплатить заказ"},{"text":"платеж не проходит успешно"},{"text":"ошибка при проведении оплаты"},{"text":"не удается произвести платеж"},{"text":"оплата не возможна сейчас"},{"text":"не могу провести платеж"}],"classificationRules":{"refs":[]},"patterns":[],"priority":0},{"id":28962551,"path":"/бухгалтерские документы и чеки","description":"","enabled":true,"shared":false,"phrases":[{"text":"не пришли бухгалтерские документы"},{"text":"не было закрывающих документов"},{"text":"не пришел чек"},{"text":"не поступили акты-сверки"},{"text":"документы не были отправлены"},{"text":"не получили подтверждающие бумаги"},{"text":"бухгалтерские документы отсутствуют"},{"text":"не было выставлено счета"},{"text":"не пришли необходимые бумаги"},{"text":"акты-сверки не поступили"},{"text":"чек не был прислан"},{"text":"документы не были получены"},{"text":"не было отправлено подтверждение"},{"text":"бухгалтерские бумаги не пришли"},{"text":"не получили необходимые документы"},{"text":"счет не был выставлен"},{"text":"не пришли документы о платеже"},{"text":"акты-сверки отсутствуют"},{"text":"не было прислано подтверждение"},{"text":"бухгалтерские документы не поступили"},{"text":"не получили чек"},{"text":"не было отправлено уведомление"},{"text":"документы о платеже не пришли"},{"text":"не пришли необходимые бумаги"},{"text":"акты-сверки не были присланы"},{"text":"бухгалтерские бумаги отсутствуют"},{"text":"не получили документы"},{"text":"не было выставлено подтверждение"},{"text":"не пришли документы о транзакции"},{"text":"не поступили бухгалтерские бумаги"},{"text":"не было отправлено уведомление о платеже"}],"classificationRules":{"refs":[]},"patterns":[],"priority":0},{"id":28962552,"path":"/разблокировка денежных средств","enabled":true,"shared":false,"phrases":[{"text":"как разблокировать денежные средства"},{"text":"как перевести деньги с резерва на счет"},{"text":"как высвободить резерв для покупки публикаций"},{"text":"я хочу освободить место в резерве чтобы купить публикации"},{"text":"мне надо сделать разблокировку денег на счете"},{"text":"процедура разблокировки средств проста"},{"text":"для разблокировки средств обратитесь в службу поддержки"},{"text":"как снять ограничения с денежных средств"},{"text":"как освободить заблокированные деньги"},{"text":"как вернуть деньги с резерва на основной счет"},{"text":"для разблокировки средств потребуется подтверждение личности"},{"text":"как снять блокировку с счета"},{"text":"как освободить средства для новых транзакций"},{"text":"как снять ограничения с резервных средств"},{"text":"как вернуть деньги с резервного счета"},{"text":"для разблокировки средств потребуется время"},{"text":"как снять блокировку с резервных средств"},{"text":"как освободить средства для покупок"},{"text":"как снять ограничения с резервных денег"},{"text":"как вернуть деньги с резервного баланса"},{"text":"для разблокировки средств потребуется документ"},{"text":"как снять блокировку с баланса"},{"text":"как освободить средства для оплаты"},{"text":"как снять ограничения с баланса"},{"text":"как вернуть деньги с резервного счета на основной"},{"text":"для разблокировки средств потребуется запрос"},{"text":"как снять блокировку с резервных денег"},{"text":"как освободить средства для транзакций"},{"text":"как снять ограничения с резервного баланса"},{"text":"как вернуть деньги с резервного счета на карту"},{"text":"для разблокировки средств потребуется подтверждение"},{"text":"как снять блокировку с резервных средств на счете"}],"classificationRules":{"refs":[]},"patterns":[],"priority":0},{"id":28962553,"path":"/не могу опубликовать","enabled":true,"shared":false,"phrases":[{"text":"опубликовать вакансию я не могу"},{"text":"подскажите почему вакансия не расместилась"},{"text":"оплатили счет вакансия не активна"},{"text":"пытаюсь разместить вакансию в доступе 10 шт а когда нажимаешь опубликовать пишет 1955 руб к оплате"},{"text":"разместила вакансию деньги списались вакансия в активных не появилась"},{"text":"я это все сделала но вакансию разместить не могу"},{"text":"не удается разместить вакансию"},{"text":"не могу опубликовать вакансию"},{"text":"вакансия не появляется в разделе активные"},{"text":"не удается активировать вакансию"},{"text":"при попытке разместить вакансию возникает ошибка"},{"text":"не могу разместить вакансию на сайте"},{"text":"вакансия не активируется"},{"text":"не удается опубликовать вакансию на платформе"},{"text":"при попытке разместить вакансию система не подтверждает"},{"text":"не могу активировать вакансию на портале"},{"text":"вакансия не появляется после оплаты"},{"text":"не удается опубликовать вакансию на dd ru"},{"text":"при попытке разместить вакансию система не принимает"},{"text":"не могу активировать вакансию на сайте dd ru"},{"text":"вакансия не появляется в списке активных"},{"text":"не удается разместить вакансию из-за ошибки"},{"text":"при попытке опубликовать вакансию система не подтверждает оплату"},{"text":"не могу активировать вакансию после оплаты"},{"text":"вакансия не появляется в активных предложениях"},{"text":"не удается разместить вакансию на платформе dd ru"},{"text":"при попытке разместить вакансию система не принимает данные"},{"text":"не могу активировать вакансию на портале dd ru"},{"text":"вакансия не появляется в разделе активные предложения"},{"text":"не удается опубликовать вакансию из-за технической ошибки"},{"text":"при попытке разместить вакансию система не подтверждает транзакцию"},{"text":"не могу активировать вакансию на сайте dd ru"},{"text":"вакансия не появляется в активных вакансиях"},{"text":"не удается разместить вакансию после оплаты"},{"text":"при попытке опубликовать вакансию система не принимает платеж"},{"text":"не могу активировать вакансию на платформе dd ru"},{"text":"вакансия не появляется в разделе активные предложения после оплаты"},{"text":"не удается разместить вакансию на сайте из-за ошибки оплаты"}],"classificationRules":{"refs":[]},"patterns":[],"priority":0},{"id":28962554,"path":"/как активировать услуги","enabled":true,"shared":false,"phrases":[{"text":"как активировать услуги"},{"text":"каким способом можно подключить услуги"},{"text":"доступ купили а контакты еще не появились"},{"text":"контактов все еще нет хотя доступ имеется и оплата прошла"},{"text":"способы активации услуг после оплаты"},{"text":"как включить услуги на dd ru"},{"text":"как подключить опции после оплаты"},{"text":"как активировать функции на дэдхантере"},{"text":"как включить доступ к услугам на dd"},{"text":"как подключить сервисы на head hunter"},{"text":"как активировать пакет услуг на dd ru"},{"text":"как включить опции после покупки"},{"text":"как подключить функции на дэдхантере"},{"text":"как активировать сервисы на head hunter"},{"text":"как включить услуги после оплаты"},{"text":"как подключить доступ к функциям на dd"},{"text":"как активировать опции на дэдхантере"},{"text":"как включить сервисы на head hunter"},{"text":"как подключить пакет услуг на dd ru"},{"text":"как активировать доступ к функциям"},{"text":"как включить опции на dd ru"},{"text":"как подключить сервисы на дэдхантере"},{"text":"как активировать функции на head hunter"},{"text":"как включить услуги после покупки"},{"text":"как подключить пакет опций на dd"},{"text":"как активировать доступ к сервисам на дэдхантере"},{"text":"как включить функции на head hunter"},{"text":"как подключить услуги после оплаты на dd ru"},{"text":"как активировать опции на дэдхантере"},{"text":"как включить сервисы на head hunter после покупки"},{"text":"как подключить функции на dd ru"},{"text":"как активировать услуги на дэдхантере"},{"text":"как включить опции на head hunter"},{"text":"как подключить доступ к функциям на dd ru"},{"text":"как активировать сервисы на дэдхантере после оплаты"}],"classificationRules":{"refs":[]},"patterns":[],"priority":0},{"id":28962555,"path":"/о себе","enabled":true,"shared":false,"phrases":[{"text":"где найти раздел о себе"},{"text":"что можно узнать в разделе о себе"},{"text":"как заполнить раздел о себе"},{"text":"какие данные указать в разделе о себе"},{"text":"раздел о себе где находится"},{"text":"какие сведения внести в раздел о себе"},{"text":"как заполнить информацию о себе"},{"text":"где раздел о себе на dd ru"},{"text":"какие данные в разделе о себе указать"},{"text":"как заполнить профиль в разделе о себе"},{"text":"какие сведения добавить в раздел о себе"},{"text":"где находится раздел о себе"},{"text":"какие данные внести в профиль о себе"},{"text":"как заполнить информацию о себе на dd ru"},{"text":"какие сведения внести в раздел о себе на сайте"},{"text":"где раздел о себе на дэдхантере"},{"text":"какие данные указать в профиле о себе"},{"text":"как заполнить раздел о себе на head hunter"},{"text":"какие сведения добавить в разделе о себе"},{"text":"где найти раздел о себе на dd ru"},{"text":"какие данные внести в раздел о себе на дэдхантере"},{"text":"как заполнить информацию о себе на head hunter"},{"text":"где раздел о себе на сайте dd ru"},{"text":"какие данные указать в профиле о себе на dd"},{"text":"как заполнить раздел о себе на портале dd ru"},{"text":"какие сведения добавить в раздел о себе на дэдхантере"},{"text":"где найти раздел о себе на платформе dd"},{"text":"какие данные внести в раздел о себе на head hunter"},{"text":"как заполнить информацию о себе на сайте dd ru"},{"text":"какие сведения в разделе о себе указать"},{"text":"какие данные добавить в профиль о себе"},{"text":"как заполнить раздел о себе на платформе dd ru"},{"text":"какие сведения внести в раздел о себе на дэдхантере"},{"text":"где найти раздел о себе на сайте head hunter"},{"text":"какие данные указать в разделе о себе на dd ru"}],"classificationRules":{"refs":[]},"patterns":[],"priority":0},{"id":28962556,"path":"/сроки хранения денег на счете","description":"","enabled":true,"shared":false,"phrases":[{"text":"когда денежные ресурсы будут недоступны для использования в системе"},{"text":"как долго могут находиться средства на счете"},{"text":"сколько времени хранятся финансовые активы в системе"},{"text":"когда средства исчезнут из системы"},{"text":"до какого момента средства будут доступны для использования"},{"text":"сколько средства могут храниться на счете если вакансии не активированы"},{"text":"как долго могут храниться денежные средства на счете пользователя"},{"text":"сколько времени могут лежать финансовые ресурсы на счете"},{"text":"когда финансовые активы будут недоступны для использования"},{"text":"до какого времени средства будут храниться на счете"},{"text":"сколько времени могут храниться денежные средства на счете если вакансии не активированы"},{"text":"как долго могут находиться финансовые ресурсы на счете пользователя"},{"text":"сколько времени хранятся денежные активы в системе"},{"text":"когда средства будут недоступны для использования в системе"},{"text":"до какого момента финансовые ресурсы будут доступны для использования"},{"text":"сколько времени могут храниться финансовые активы на счете если вакансии не активированы"},{"text":"как долго могут храниться денежные ресурсы на счете пользователя"},{"text":"сколько времени могут находиться финансовые активы на счете"},{"text":"когда денежные средства будут недоступны для использования"},{"text":"до какого времени финансовые ресурсы будут храниться на счете"},{"text":"сколько времени могут храниться денежные активы на счете"},{"text":"как долго могут находиться финансовые ресурсы на счете если вакансии не активированы"},{"text":"сколько времени хранятся финансовые активы в системе если вакансии не активированы"},{"text":"когда финансовые ресурсы будут недоступны для использования в системе"},{"text":"до какого момента денежные средства будут доступны для использования"},{"text":"сколько времени могут храниться финансовые ресурсы на счете если вакансии не активированы"},{"text":"как долго могут храниться денежные активы на счете пользователя если вакансии не активированы"},{"text":"сколько времени могут находиться финансовые активы на счете если вакансии не активированы"}],"classificationRules":{"refs":[]},"patterns":[],"priority":0},{"id":28962557,"path":"/какие услуги подключены","enabled":true,"shared":false,"phrases":[{"text":"какие услуги у меня подключены"},{"text":"до какого времени действует услуга"},{"text":"сколько вакансий я могу еще разместить"},{"text":"сколько контактов я уже посмотрел"},{"text":"сколько контактов я могу посмотреть"},{"text":"какие функции мне доступны"},{"text":"какие опции у меня активированы"},{"text":"какие пакеты услуг я приобрел"},{"text":"какие дополнительные услуги я заказал"},{"text":"какие возможности мне открыты"},{"text":"какие сервисы у меня подключены"},{"text":"что входит в мой пакет услуг"},{"text":"какие услуги я использую"},{"text":"какие услуги я оплатил"},{"text":"какие опции мне доступны"},{"text":"какие функции я активировал"},{"text":"какие дополнительные сервисы у меня есть"},{"text":"какие возможности мне доступны"},{"text":"какие услуги мне подключены"},{"text":"до какого срока действуют мои услуги"},{"text":"сколько вакансий я могу разместить"},{"text":"сколько контактов доступно для просмотра"},{"text":"какие пакеты услуг я приобрел"},{"text":"какие опции я использую"},{"text":"какие сервисы я активировал"},{"text":"какие возможности мне открыты"},{"text":"что входит в мой пакет"},{"text":"какие услуги у меня активны"},{"text":"какие функции мне доступны сейчас"},{"text":"какие дополнительные сервисы я заказал"},{"text":"сколько вакансий доступно для размещения"},{"text":"сколько контактов я могу просмотреть"},{"text":"какие услуги я уже подключил"}],"classificationRules":{"refs":[]},"patterns":[],"priority":0},{"id":28962558,"path":"/сроки поступления средств","enabled":true,"shared":false,"phrases":[{"text":"каким способом оплатить быстрее"},{"text":"когда поступят деньги"},{"text":"почему деньги так долго поступают"},{"text":"оплатили утром когда придут деньги"},{"text":"как долго ждать поступления средств"},{"text":"когда средства поступят на счет"},{"text":"почему задерживаются поступления"},{"text":"как ускорить поступление денег"},{"text":"оплатили заказ когда поступят средства"},{"text":"как проверить статус поступления средств"},{"text":"когда можно ожидать поступления денег"},{"text":"почему задерживаются средства"},{"text":"когда средства будут зачислены"},{"text":"почему оплата не поступила"},{"text":"как ускорить процесс поступления средств"},{"text":"оплатили услугу когда поступят деньги"},{"text":"как узнать когда поступят средства"},{"text":"когда ожидать поступления оплаты"},{"text":"почему задерживаются поступления на счет"},{"text":"как проверить поступление денег"},{"text":"когда средства поступят после оплаты"},{"text":"почему оплата не зачислена"},{"text":"как ускорить поступление оплаты"},{"text":"оплатили вакансию когда поступят деньги"},{"text":"как узнать статус поступления оплаты"},{"text":"когда можно ждать поступления средств"},{"text":"почему задерживаются поступления после оплаты"},{"text":"как проверить поступление оплаты"},{"text":"когда средства будут доступны"},{"text":"почему оплата не поступила на счет"},{"text":"как ускорить процесс зачисления средств"},{"text":"оплатили пакет когда поступят деньги"},{"text":"как узнать когда средства поступят на счет"}],"classificationRules":{"refs":[]},"patterns":[],"priority":0},{"id":28962559,"path":"/отмена услуг или возврат средств","enabled":true,"shared":false,"phrases":[{"text":"случайно разместила не ту вакансию можно ли ее удалить и вернуть деньги за размещение"},{"text":"удалили мою вакансию просьба вернуть деньги"},{"text":"как нам вернуть деньги на счет в кабинете dd ru потому что вакансия не прошла модерацию"},{"text":"прошу вернуть деньги услуга не оказана"},{"text":"могу ли я оформить возврат денег и аннулировать вакансию"},{"text":"можно сделать возврат денег я хотела оплатить как раз эту услугу а оплатила не тот пакет"},{"text":"как вернуть средства за неиспользованную услугу"},{"text":"как аннулировать оплату и вернуть деньги"},{"text":"прошу вернуть средства услуга не была предоставлена"},{"text":"как получить возврат средств за неактивированную вакансию"},{"text":"как отменить услугу и вернуть деньги"},{"text":"случайно оплатила лишнюю вакансию можно ли вернуть деньги"},{"text":"как снять средства с аккаунта если услуга не нужна"},{"text":"как оформить возврат средств за неиспользованную вакансию"},{"text":"как аннулировать платеж и вернуть деньги"},{"text":"прошу вернуть деньги за неактивированную услугу"},{"text":"как получить возврат за неподтвержденную вакансию"},{"text":"как вернуть оплату за неиспользованную услугу"},{"text":"как отменить заказ и вернуть деньги"},{"text":"как аннулировать покупку и вернуть средства"},{"text":"прошу вернуть средства за неактивированную вакансию"},{"text":"как снять блокировку с оплаты и вернуть деньги"},{"text":"как отменить транзакцию и вернуть средства"},{"text":"как получить возврат за неподтвержденную услугу"},{"text":"как вернуть оплату за неактивированную вакансию"},{"text":"как отменить платеж и вернуть деньги"},{"text":"как аннулировать заказ и вернуть средства"},{"text":"как оформить возврат за неиспользованную услугу"},{"text":"как вернуть средства за неподтвержденную вакансию"},{"text":"как снять оплату и вернуть деньги"},{"text":"как получить возврат за неактивированную услугу"}],"classificationRules":{"refs":[]},"patterns":[],"priority":0},{"id":28962560,"path":"/удаленная работа","enabled":true,"shared":false,"phrases":[{"text":"найти удалённую работу"},{"text":"ищу работу удалённо"},{"text":"изменить статус удалённо"},{"text":"указать о работе только удалённо"},{"text":"ищу удалённую работу"},{"text":"поставить фильтр удалённая работа"},{"text":"ищу удалённую вакансию"},{"text":"работа дома"},{"text":"работа дистанционно"},{"text":"работа без опыта удалённо"},{"text":"график работы удаленно"},{"text":"ищу вакансию с удалённым форматом"},{"text":"найти работу на дому"},{"text":"указать предпочтение удалённой работе"},{"text":"ищу дистанционную работу"},{"text":"указать в резюме готовность работать удалённо"},{"text":"ищу вакансии для удалённой работы"},{"text":"работа из дома"},{"text":"работа в удаленном формате"},{"text":"ищу вакансии с возможностью удалённой работы"},{"text":"указать вакансию только удалённую"},{"text":"ищу работу с удалённым доступом"},{"text":"ищу вакансию с дистанционным форматом"},{"text":"работа в удаленном режиме"},{"text":"ищу вакансии для работы из дома"},{"text":"указать готовность к удалённой работе"},{"text":"ищу работу с возможностью дистанционной работы"},{"text":"указать вакансию с удалённым режимом"},{"text":"ищу работу с удалённым графиком"},{"text":"работа на дому"},{"text":"ищу вакансии с дистанционным доступом"},{"text":"указать предпочтение работе из дома"},{"text":"ищу работу с удалённым форматом"},{"text":"ищу вакансии с возможностью работы на дому"}],"classificationRules":{"refs":[]},"patterns":[],"priority":0},{"id":28962561,"path":"/доступ к базе резюме","enabled":true,"shared":false,"phrases":[{"text":"доступ к базе резюме"},{"text":"есть ли доступ к базе резюме в белоруссии в городе минск "},{"text":"сколько стоит доступ к базе резюме"},{"text":"где оплатить доступ к контактам"},{"text":"как купить доступ к контактам"},{"text":"как получить доступ к базе резюме в москве"},{"text":"интересует доступ к базе резюме специалистов в спб подскажите как это сделать"},{"text":"как открыть доступ к резюме в екатеринбурге какие тарифы действуют"},{"text":"необходим доступ к базе резюме разработчиков в новосибирске какие условия"},{"text":"как получить доступ к резюме менеджеров по продажам в казани"},{"text":"предоставляете ли вы доступ к базе резюме в нижнем новгороде если да то как"},{"text":"интересует доступ к резюме маркетологов в челябинске что для этого нужно"},{"text":"как открыть доступ к базе резюме в самаре"},{"text":"есть ли возможность получить доступ к базе резюме итспециалистов в омске"},{"text":"как получить доступ к базе резюме в ростовенадону"},{"text":"хочу получить доступ к базе резюме юристов в уфе какие условия"},{"text":"как мне получить доступ к базе резюме в красноярске"},{"text":"подскажите как получить доступ к базе резюме в воронеже"},{"text":"интересует доступ к базе резюме инженеров в перми"},{"text":"как получить доступ к базе резюме в волгограде"},{"text":"как открыть доступ к базе резюме в краснодаре"},{"text":"интересует база резюме в саратове как получить доступ"},{"text":"как получить доступ к базе резюме в тюмени"},{"text":"нужен доступ к базе резюме в тольятти какие варианты подключения"},{"text":"как получить доступ к базе резюме в ижевске"}],"classificationRules":{"refs":[]},"patterns":[],"priority":0},{"id":28962562,"path":"/изменить фото","enabled":true,"shared":false,"phrases":[{"text":"удалить фото"},{"text":"как поставить фото на резюме"},{"text":"добавить фото в резюме"},{"text":"вставить фото в резюме"},{"text":"сменить фотографию в резюме"},{"text":"поменять главное фото"},{"text":"поменять фото"},{"text":"изменить фото профиля"},{"text":"поменять фото профиля"},{"text":"установить фото"},{"text":"сменить фото профиля"},{"text":"не могу поменять фото"},{"text":"отсутствует функция сменить фото"},{"text":"не получается добавить фотографию в разделе профиль"},{"text":"фото не получается вставить "},{"text":"разместить фото"},{"text":"поменять фото на моём аккаунте"},{"text":"поменять аватарку"},{"text":"не могу поставить фото на аватар"},{"text":"прикрепить фото к резюме"},{"text":"смена фото"},{"text":"поменять фото анкеты"},{"text":"убрать фото профиля"},{"text":"изменить фотографию"},{"text":"как скрыть свои фото"},{"text":"поставить фото"},{"text":"поменять аватарку"},{"text":"поставить аватарку"},{"text":"удалить фото из профиля"},{"text":"фото в резюме"}],"classificationRules":{"refs":[]},"patterns":[],"priority":0},{"id":28962563,"path":"/условия действия вакансий","enabled":true,"shared":false,"phrases":[{"text":"как действуют вакансии"},{"text":"в каком блоке будет опубликована вакансия"},{"text":"на каком месте будет вакансия"},{"text":"вакансии размещаются календарные дни"},{"text":"вакансии размещаются только по будням"},{"text":"будут ли обновляться вакансии"},{"text":"меня интересует на каких условиях действуют вакансии"},{"text":"расскажите мне об условиях вакансий"},{"text":"помогите я не понимаю по условиям"},{"text":"где можно ознакомиться с полными условиями действия вакансий на вашем сервисе"},{"text":"я бы хотел получить консультацию по условиям"},{"text":"условия действия вакансий мне нужны"},{"text":"хочу попасть в раздел условия действия вакансий"},{"text":"расскажите мне про условия действия у вакансий"},{"text":"как действуют вакансии на каких условиях"},{"text":"как условия действия вакансий отличаются для разных тарифных планов"},{"text":"мне хотелось бы понимать по условиям действия вакансий"},{"text":"на каких условиях на вашем сайте вакансии действуют"},{"text":"хочу понимать условия по типам вакансий"},{"text":"как между собой различаются условия по типам у вакансий"},{"text":"у вакансий разные типы же бывают в чем отличие"},{"text":"расскажите про условия у разных типов вакансий"},{"text":"хочу понимать сколько длятся вакансии конкретного типа"},{"text":"мне неясны условия действия вакансий"},{"text":"в каком блоке вы публикуете мои вакансии"}],"classificationRules":{"refs":[]},"patterns":[],"priority":0},{"id":28962564,"path":"/срок размещения вакансии","enabled":true,"shared":false,"phrases":[{"text":"срок размещения вакансии"},{"text":"на сколько размещается вакансия"},{"text":"на сколько размещается публикация стандарт"},{"text":"на какой срок размещается вакансия"},{"text":"как узнать в какое время точно вакансия уйдет в архив где это посмотреть"},{"text":"подскажите можно ли посмотреть время когда вакансия уйдет в архив"},{"text":"какой срок размещения предусмотрен для вакансии с моим тарифом"},{"text":"на какой период времени размещается вакансия при стандартной публикации"},{"text":"сколько действует размещение вакансии после оплаты"},{"text":"какой срок действия имеет моя опубликованная вакансия"},{"text":"укажите пожалуйста срок размещения для вакансии которую я только что опубликовал"},{"text":"где я могу увидеть срок окончания размещения моей вакансии"},{"text":"на какой срок обычно публикуются вакансии на вашем сервисе"},{"text":"какой максимальный срок публикации вакансии возможен"},{"text":"сколько времени будет активна моя вакансия после одобрения модератором"},{"text":"каков стандартный срок размещения вакансии при использовании бесплатного тарифа"},{"text":"через сколько дней моя вакансия будет снята с публикации"},{"text":"где найти информацию о сроке размещения моей вакансии в личном кабинете"},{"text":"как можно узнать дату окончания размещения моей вакансии"},{"text":"какой срок действия у вакансии если ее не поднимать в поиске"},{"text":"на какой срок распространяется промо размещение вакансии"},{"text":"сколько времени моя вакансия будет видна соискателям"},{"text":"как долго обычно ищут кандидатов через ваш сервис какой средний срок размещения вакансии"},{"text":"если я не найду кандидата за стандартный срок размещения что происходит"},{"text":"в течение какого времени моя вакансия будет отображаться в результатах поиска"},{"text":"какой срок публикации вакансии подразумевает мой пакет услуг"}],"classificationRules":{"refs":[]},"patterns":[],"priority":0},{"id":28962565,"path":"/портфолио","enabled":true,"shared":false,"phrases":[{"text":"добавить портфолио"},{"text":"как разместить в портфолио видео"},{"text":"раздел портфолио"},{"text":"прикрепить портфолио к резюме"},{"text":"загрузить портфолио"},{"text":"удалить изображение с портфолио"},{"text":"подгрузить изображение в портфолио"},{"text":"какие фото загрузить в портфолио"},{"text":"что загрузить в портфолио"},{"text":"оформить портфолио"},{"text":"работы для портфолио"},{"text":"не даёт загрузить портфолио"},{"text":"не могу загрузить в портфолио"},{"text":"нет графы портфолио"},{"text":"в портфолио указать ссылку"},{"text":"не видны фото из портфолио"}],"classificationRules":{"refs":[]},"patterns":[],"priority":0},{"id":28962566,"path":"/докупка контактов","enabled":true,"shared":false,"phrases":[{"text":"подскажите как оплатить докупку контактов по москве"},{"text":"докупка контактов на какой срок дается"},{"text":"покупка услуг по подбору персонала докупка услуг изменение региона"},{"text":"не могу найти услугу докупка контактов"},{"text":"у меня на балансе больше двух тысяч как их использовать для докупки контактов для просмотра контактов кандидатов"},{"text":"при докупке контактов какой у них срок действия"},{"text":"недавно была возможность приобрести немного контактов эту услугу отключили"},{"text":"как работает услуга докупки контактов"},{"text":"сколько стоит докупить контакты для вакансии название вакансии"},{"text":"какое минимальное количество контактов можно докупить"},{"text":"есть ли скидки на докупку большого количества контактов"},{"text":"на какой срок действуют докупленные контакты"},{"text":"что происходит с неиспользованными контактами после истечения срока"},{"text":"можно ли докупить контакты для нескольких вакансий сразу"},{"text":"какие способы оплаты доступны для докупки контактов"},{"text":"как быстро активируются докупленные контакты"},{"text":"куда обращаться если возникли проблемы с докупкой контактов"},{"text":"можно ли вернуть деньги за неиспользованные докупленные контакты"},{"text":"как часто можно докупать контакты для одной и той же вакансии"},{"text":"есть ли какие-то ограничения по докупке контактов"},{"text":"можно ли докупить контакты если основной тариф уже истек"},{"text":"как отслеживать количество оставшихся докупленных контактов"},{"text":"есть ли пробный период для услуги докупки контактов"},{"text":"влияет ли докупка контактов на позицию вакансии в поисковой выдаче"},{"text":"можно ли докупить контакты для конкретных кандидатов"},{"text":"предоставляете ли вы статистику по использованию докупленных контактов"},{"text":"можно ли докупить контакты для кандидатов которые уже откликнулись на вакансию"}],"classificationRules":{"refs":[]},"patterns":[],"priority":0},{"id":28962567,"path":"/как поднять вакансию в поиске","enabled":true,"shared":false,"phrases":[{"text":"скажите мои размещенные вакансии почему не в топе сейчас как сделать чтобы они были в топе"},{"text":"есть ли у вас услуга по улучшению вакансии когда она держится в топе"},{"text":"как объявление поставить в топ"},{"text":"оплата топ поиска"},{"text":"топ поиск"},{"text":"как можно поднять объявление"},{"text":"поднять вакансию в топ"},{"text":"как подключить услугу топ поиска к вакансии менеджер по продажам в астане"},{"text":"как поднять мою вакансию в результатах поиска"},{"text":"какие способы есть для поднятия вакансии в поиске"},{"text":"сколько стоит поднять вакансию в поиске"},{"text":"на какой срок вакансия поднимается в поиске после оплаты"},{"text":"как часто можно поднимать вакансию в поиске"},{"text":"какие факторы влияют на позицию моей вакансии в поиске"},{"text":"есть ли автоматический способ поднимать вакансию в поиске регулярно"},{"text":"как работает опция поднятия вакансии в поиске"},{"text":"что нужно сделать чтобы моя вакансия чаще появлялась в поиске"},{"text":"как продвинуть вакансию в поиске чтобы привлечь больше кандидатов"},{"text":"какие преимущества дает поднятие вакансии в поиске"},{"text":"есть ли гарантия что моя вакансия будет на первой странице после поднятия"},{"text":"как отслеживать эффективность поднятия вакансии в поиске"},{"text":"можно ли поднять вакансию в поиске только в определенные дни недели или время суток"},{"text":"существуют ли разные тарифы на поднятие вакансии в поиске"},{"text":"как правильно оформить вакансию чтобы она лучше ранжировалась в поиске"},{"text":"есть ли инструкция по поднятию вакансии в поиске"},{"text":"как работает алгоритм поиска на вашем сервисе"},{"text":"как часто обновляется поисковая выдача вакансий"},{"text":"можно ли поднять в поиске сразу несколько моих вакансий"},{"text":"как сделать так чтобы мое резюме выпадало в поиске на позицию"}],"classificationRules":{"refs":[]},"patterns":[],"priority":0},{"id":28962568,"path":"/действия с вакансией","enabled":true,"shared":false,"phrases":[{"text":"как разместить вакансии из архива"},{"text":"как разместить вакансии из шаблона"},{"text":"как разместить вакансии из черновика"},{"text":"как разместить новую вакансию"},{"text":"как обновить вакансию"},{"text":"как продлить вакансию"},{"text":"как улучшить вакансию"},{"text":"как из стандарта сделать стандарт+"},{"text":"как из стандарта сделать премиум"},{"text":"как из стандарт+ сделать премиум"},{"text":"как из премиум сделать стандарт+"},{"text":"как подключить автопродление"},{"text":"нам нужен новый сотрудник как вакансию поместить"},{"text":"прошу добавить к вакансии возможность отклика без резюме если такая опция доступна"},{"text":"хотел бы узнать можно ли выделить вакансию как горящую или срочную если да то как это можно сделать"},{"text":"хочу поменять тип вакансии"},{"text":"мне нужно из премиум вакансии сделать обычную"},{"text":"сделайте из моей обычной вакансии премиум или еще какую-нибудь"},{"text":"есть ли у вас автопродление хочу подключить к своей вакансии"},{"text":"разместил у вас вакансию как её продлить автоматически"},{"text":"могу ли я поменять статус вакансии на премиум"},{"text":"продлите мне вакансию менеджера мы так никого и не нашли"},{"text":"мне нужно внести изменения в объявление как это сделать"},{"text":"я бы хотел внести изменения в вакансию нужно заменить старый текст на новый"},{"text":"можно ли как-нибудь улучшить вакансию а то никто не отзывается"}],"classificationRules":{"refs":[]},"patterns":[],"priority":0},{"id":28962569,"path":"/видимость резюме","enabled":true,"shared":false,"phrases":[{"text":"не ищу работу скройте моё резюме"},{"text":"скрыть резюме из поиска можно как-то"},{"text":"изменить видимость моего резюме для компаний"},{"text":"я нашёл работу уберите моё резюме из выдачи"},{"text":"изменить видимость объявления о поиске"},{"text":"отключить видимость моего резюме нужно"},{"text":"могу ли я как-то отрегулировать видимость"},{"text":"проверить видимость резюме для работодателей"},{"text":"убрать видимость резюме из поиска"},{"text":"скрыть видимость резюме на время пока я не ищу"},{"text":"скрыть резюме из общей выдачи"},{"text":"скройте моё резюме из выдачи для магазинов"},{"text":"я устал от того что мне названивают по неподходящим вакансиям уберите мое резюме из поиска"},{"text":"скройте мое резюме из результатов поиска"},{"text":"прошу вас сделать мое резюме невидимым для работодателей"},{"text":"хочу чтобы мое резюме больше не отображалось в поисковой выдаче"},{"text":"сделайте мое резюме приватным"},{"text":"я хочу чтобы мое резюме стало недоступным для просмотра"},{"text":"я хочу ограничить доступ к моему резюме сделайте его невидимым"},{"text":"как мне сделать так чтобы рекрутеры больше не видели мое резюме"},{"text":"сделайте так чтобы мое резюме видели только те компании которым я его отправлю"},{"text":"как мне настроить видимость резюме чтобы оно было скрыто из поиска"},{"text":"как можно полностью скрыть резюме от просмотра другими пользователями"},{"text":"сделайте так чтобы мое резюме не появлялось в списках рекомендованных кандидатов"},{"text":"прошу сделать мое резюме недоступным для автоматического поиска"}],"classificationRules":{"refs":[]},"patterns":[],"priority":0},{"id":28962570,"path":"/мне предлагают удалить резюме","enabled":true,"shared":false,"phrases":[{"text":"не могу просмотреть свои резюме и отредактировать их ваша система предлагает их просто удалить"},{"text":"после нажатия на название резюме оно не открывается вместо этого открывается окно в котором мне предлагают удалить резюме"},{"text":"не могу отредактировать резюме после обновления выбрасывает на страницу удалить резюме"},{"text":"сайт при нажатии кнопки редактировать резюме предлагает удалить одно из двух резюме"},{"text":"предлагается только удалить резюме которыми не пользуюсь"},{"text":"всплывает окно что я должен удалить резюме которым не пользуюсь "},{"text":"нажимаешь редактировать выходит удалить резюме"},{"text":"просит удалить неактуальные или продолжить без изменений"},{"text":"не даёт редактировать предлагает только удалить "},{"text":"когда нажимая редактировать появляется раздел удалите резюме которым не пользуетесь"},{"text":"при нажатии на название резюме выбрасывает на страницу где можно только удалить его возможности редактирования нет"},{"text":"нажимаешь редактировать выходит удалить резюме"},{"text":"меня просят удалить резюме которыми я не пользуюсь"},{"text":"почему требуете удалить мои активные резюме которые я использую"},{"text":"невозможно редактировать система предлагает только удалить резюме"},{"text":"при нажатии на резюме он предлагает выбрать одно неактуальное и удалить его"},{"text":"не могу зайти в свой профиль предлагает удалить одно из моих резюме"},{"text":"при клике на редактировать или любую другую опцию мне предлагают их просто удалить"},{"text":"кнопка редактировать просит удалить резюме"},{"text":"выходит окно в котором предлагается удалить существующие резюме без сохранения"},{"text":"нажимаю редактировать меня перебрасывает в окно где меня просят удалить резюме которыми я не пользуюсь"},{"text":"когда нажимаю на редактирование выходит страница на удаление резюме"},{"text":"не могу зайти не в одно из двух своих резюме чтобы их подкорректировать"},{"text":"я жму редактировать резюме мне предлагается стереть не используемое резюме"},{"text":"мне постоянно предлагают удаление резюме а не редактирование почему"}],"classificationRules":{"refs":[]},"patterns":[],"priority":0},{"id":28962571,"path":"/изменить персональные данные и знание языков","enabled":true,"shared":false,"phrases":[{"text":"как изменить в профиле фамилию и данные"},{"text":"не могу изменить фамилию"},{"text":"хотела поменять фамилию в резюме"},{"text":"изменить фамилию в профиле"},{"text":"изменить фамилию и имя в профиле"},{"text":"изменить данные в имени и фамилии в профиле"},{"text":"хотелось поменять фамилию имя отчество"},{"text":"изменить фамилию в резюме"},{"text":"изменилась фамилия в паспорте"},{"text":"моя фамилия в профиле написана не правильно"},{"text":"как изменить формат фио"},{"text":"изменились имя и фамилия по паспорту"},{"text":"моя фамилия изменилась "},{"text":"у меня указана только фамилия как добавить имя"},{"text":"как в резюме добавить фио"},{"text":"у меня высвечивается старое фио "},{"text":"изменить номер телефона и фамилию"},{"text":"изменить пол на женский я по ошибке не тот поставила"},{"text":"возраст поменять не могу в своём резюме"},{"text":"указать в резюме свой личный возраст"},{"text":"скрыть день рождения и фамилию"},{"text":"изменить опечатку в дате рождения"},{"text":"сменить город поменять город в резюме"},{"text":"где в резюме найти города куда готова переехать"},{"text":"выбрать нужный город проживания"},{"text":"хочу указать что я говорю по английски"},{"text":"владею турецким можно это в резюме пометить"},{"text":"получила сертификат toefl можно это добавить в резюме"},{"text":"я бы хотела указать что я знаю японский"},{"text":"у меня немецкий в школе был мне бы это прописать в навыки"},{"text":"я бы хотела пометить владение китайским"}],"classificationRules":{"refs":[]},"patterns":[],"priority":0},{"id":28962572,"path":"/город поиска вакансий","enabled":true,"shared":false,"phrases":[{"text":"как добавить город видимости для просмотра"},{"text":"как выбрать свой город поиска работы"},{"text":"изменить город в разделе поиск вакансий"},{"text":"показывается ли мое резюме московским компаниям"},{"text":"в каком городе будет видно мое резюме"},{"text":"почему я вижу вакансии по всей россии а не по своему городу"},{"text":"как настроить чтобы не показывало в москве"},{"text":"хочу найти работу по всем регионам но показывает вакансии только из моего города"},{"text":"почему то по умолчанию мне предлагают вакансии из волгограда а не из москвы"},{"text":"почему у меня показывается ставрополь и армавир если как вы пишите показываются все города рядом"},{"text":"я не хочу видеть в своей подборке вакансии из питера"},{"text":"как перейти на другой город чтобы там смотреть вакансии"},{"text":"вакансии не из моего города"},{"text":"я собираюсь переезжать можно мне вакансии показать другого города"},{"text":"хочу чтобы высвечивались вакансии в москве"},{"text":"собираюсь в другом городе работу поискать "},{"text":"можете мне показывать объявления из самары"},{"text":"мне нужно чтобы были вакансии из питера а тут из новгорода"},{"text":"хочу сменить город поиска работы"},{"text":"может в москве получше с работой покажите мне их вакансии"},{"text":"мне не подходит работа в моем городе могу я другие посмотреть"},{"text":"покажите мне подходящие должности но в саратове"},{"text":"я буду переезжать во владик какая там есть работа"},{"text":"семья переезжает могу я в другом городе работу поискать"},{"text":"хотел бы сменить радиус поиска вакансий"},{"text":"не показывайте мне вакансии из тулы"},{"text":"мне больше не нужны вакансии петропавловска"},{"text":"я больше не хочу искать работу в москве"},{"text":"а почему мне вакансии только из нижнего выдает поиск"}],"classificationRules":{"refs":[]},"patterns":[],"priority":0}]